{
  "views": {
    "forgot-password": [
      {
        "placeholder": "E-mail Address",
        "name": "email",
        "type": "email",
        "icon": "mail"
      }
    ],
    "login": [
      {
        "name": "username",
        "type": "text",
        "placeholder": "User Name",
        "icon": "user"
      },
      {
        "name": "password",
        "type": "password",
        "placeholder": "Password",
        "icon": "lock"
      }
    ],
    "register": [
      {
        "name": "username",
        "type": "text",
        "placeholder": "User Name",
        "icon": "user"
      },
      {
        "placeholder": "E-mail Address",
        "name": "email",
        "type": "email",
        "icon": "mail"
      },
      {
        "name": "password",
        "type": "password",
        "placeholder": "Password",
        "icon": "lock"
      },
      {
        "name": "confirmPassword",
        "type": "password",
        "placeholder": "Confirm Password",
        "icon": "lock"
      }
    ],
    "reset-password": [
      {
        "name": "password",
        "type": "password",
        "placeholder": "Password",
        "icon": "lock"
      },
      {
        "name": "confirmPassword",
        "type": "password",
        "placeholder": "Confirm Password",
        "icon": "lock"
      }
    ]
  },
  "data": {
    "login": {
      "username": "",
      "password": ""
    },
    "forgot-password": {
      "email": ""
    },
    "register": {
      "username": "",
      "password": "",
      "confirmPassword": "",
      "email": ""
    },
    "reset-password": {
      "password": "",
      "passwordConfirmation": "",
      "code": ""
    }
  }
}
